venv/__init__.py
venv/AaSystem/AriotsShield.py
venv/AaSystem/Colors.py
venv/AaSystem/__init__.py
venv/AttackAgent/__init__.py
venv/AttackAgent/AttackAgentSystemCommands/AaSystemCommands.py
venv/AttackAgent/AttackAgentSystemCommands/__init__.py
venv/AttackAgent/BaseCommands/BaseCommands.py
venv/AttackAgent/BaseCommands/CommandExecutor.py
venv/AttackAgent/BaseCommands/CommandQueue.py
venv/AttackAgent/BaseCommands/RequestBuilder.py
venv/AttackAgent/BaseCommands/__init__.py
venv/AttackAgent/Bash/BashCommandExecutor.py
venv/AttackAgent/Bash/BashCommands.py
venv/AttackAgent/Bash/__init__.py
venv/AttackAgent/BatchCommands/BatchCommandHandler.py
venv/AttackAgent/BatchCommands/__init__.py
Ariots_Attack_Agent-0.0.1.dist-info/LICENSE
Ariots_Attack_Agent-0.0.1.dist-info/METADATA
Ariots_Attack_Agent-0.0.1.dist-info/WHEEL
Ariots_Attack_Agent-0.0.1.dist-info/top_level.txt
Ariots_Attack_Agent-0.0.1.dist-info/RECORD
