Metadata-Version: 2.1
Name: Ariots-Attack-Agent
Version: 0.0.1
Summary: Microsoft ArIoTS Attack Agent
Home-page: UNKNOWN
Author: Yuval Feldman
Author-email: yufeldma@microsoft.com
License: UNKNOWN
Platform: UNKNOWN
Classifier: Programming Language :: Python :: 3
Classifier: License :: OSI Approved :: MIT License
Classifier: Operating System :: OS Independent
